{
    "name": "DepreciationCalculation",
    "fields": [
        {
            "fieldName": "monthType",
            "fieldType": "MonthType",
            "fieldValues": "JANUARY,FEBRUARY,MARCH,APRIL,MAY,JUNE,JULY,AUGUST,SEPTEMBER,OCTOBER,NOVEMBER,DECEMBER"
        },
        {
            "fieldName": "isExecuted",
            "fieldType": "Boolean"
        },
        {
            "fieldName": "createdBy",
            "fieldType": "String"
        },
        {
            "fieldName": "createdOn",
            "fieldType": "Instant"
        },
        {
            "fieldName": "modifiedBy",
            "fieldType": "String"
        },
        {
            "fieldName": "modifiedOn",
            "fieldType": "Instant"
        }
    ],
    "relationships": [
        {
            "relationshipType": "many-to-one",
            "otherEntityName": "financialAccountYear",
            "otherEntityRelationshipName": "depreciationCalculation",
            "relationshipName": "financialAccountYear",
            "otherEntityField": "id"
        }
    ],
    "changelogDate": "20200822102628",
    "entityTableName": "depreciation_calculation",
    "dto": "mapstruct",
    "pagination": "infinite-scroll",
    "service": "serviceClass",
    "jpaMetamodelFiltering": true,
    "fluentMethods": true,
    "clientRootFolder": "",
    "applications": "*"
}